container2dict/__init__.py
container2dict/container2dict.py
container2dict-0.0.1.dist-info/METADATA
container2dict-0.0.1.dist-info/WHEEL
container2dict-0.0.1.dist-info/top_level.txt
container2dict-0.0.1.dist-info/RECORD
