Metadata-Version: 2.1
Name: container2dict
Version: 0.0.1
Summary: two container to dictionary
Home-page: https://pypi.org/
Author: derek
Author-email: derektmq@gmail.com
License: MIT Licence
Keywords: pip,Bwaaah
Platform: any
